[
  {
    "model": "applicant.applicant",
    "pk": 1,
    "fields": {
      "full_name": "Иванов Иван Иванович",
      "citizenship": "Россия",
      "nationality": "Русский",
      "birth_date": "2005-03-12",
      "birth_place": "г. Казань",
      "address": "г. Казань, ул. Ленина, д. 5",
      "address_actual": "г. Казань, ул. Ленина, д. 5",
      "passport_division_code": "123456",
      "passport_registration_date": "2021-03-04",
      "certificate_series": "12345678912345",
      "certificate_issued_date": "2023-06-30",
      "graduation_year": 2023,
      "graduation_institution": "МАОУ СОШ №12",
      "passport_series": "1234",
      "passport_number": "567890",
      "passport_issued_by": "УФМС по РТ",
      "passport_issued_date": "2021-03-04",
      "inn": "123456789012",
      "snils": "12345678900",
      "medical_policy": "ЧМ 12323432434",
      "military_id": true,
      "student_phone": "+7-987-654-32-10",
      "student_email": "ivanov@example.com",
      "mother_name": "Иванова Мария Петровна",
      "mother_phone": "+7-987-111-22-33",
      "mother_job": "ООО Медцентр, бухгалтер",
      "mother_passport_series": "5678",
      "mother_passport_number": "901234",
      "mother_passport_issued_by": "УФМС по РТ",
      "mother_passport_issued_date": "2020-03-04",
      "father_name": "Иванов Петр Сергеевич",
      "father_phone": "+7-987-222-33-44",
      "father_job": "ЗАО Завод, инженер",
      "father_passport_series": "9012",
      "father_passport_number": "345678",
      "father_passport_issued_by": "УФМС по РТ",
      "father_passport_issued_date": "2020-03-04",
      "documents_delivered": true,
      "specialty": "nursing_9",
      "grade_russian": 4,
      "grade_biology": 5,
      "grade_chemistry": 4,
      "grade_math": 4,
      "grade_language": 5,
      "grade_physics": 3,
      "average_grade": 4.2,
      "admission_type": "бюджет",
      "needs_dormitory": true,
      "priority_enrollment": "none",
      "preferential_enrollment": "none",
      "enrolled": false,
      "submitted_at": "2025-06-01T12:00:00Z"
    }
  },
  {
    "model": "applicant.applicant",
    "pk": 2,
    "fields": {
      "full_name": "Петрова Анна Сергеевна",
      "citizenship": "Россия",
      "nationality": "Татарка",
      "birth_date": "2006-11-25",
      "birth_place": "г. Альметьевск",
      "address": "г. Альметьевск, ул. Победы, д. 10",
      "address_actual": "г. Альметьевск, ул. Победы, д. 10",
      "passport_division_code": "654321",
      "passport_registration_date": "2020-03-04",
      "certificate_series": "12345678912345",
      "certificate_issued_date": "2023-06-30",
      "graduation_year": 2023,
      "graduation_institution": "Лицей №5",
      "passport_series": "4321",
      "passport_number": "098765",
      "passport_issued_by": "УФМС по РТ",
      "passport_issued_date": "2020-03-04",
      "inn": "987654321098",
      "snils": "98765432199",
      "medical_policy": "АБ",
      "military_id": false,
      "student_phone": "+7-927-333-44-55",
      "student_email": "petrova@example.com",
      "mother_name": "Петрова Светлана Викторовна",
      "mother_phone": "+7-927-555-66-77",
      "mother_job": "Школа №5, учитель",
      "mother_passport_series": "3456",
      "mother_passport_number": "789012",
      "mother_passport_issued_by": "УФМС по РТ",
      "mother_passport_issued_date": "2019-03-04",
      "father_name": "Петров Сергей Николаевич",
      "father_phone": "+7-927-666-77-88",
      "father_job": "Нефтебаза, оператор",
      "father_passport_series": "7890",
      "father_passport_number": "123456",
      "father_passport_issued_by": "УФМС по РТ",
      "father_passport_issued_date": "2019-03-04",
      "documents_delivered": true,
      "specialty": "nursing_9",
      "grade_russian": 5,
      "grade_biology": 4,
      "grade_chemistry": 5,
      "grade_math": 5,
      "grade_language": 4,
      "grade_physics": 4,
      "average_grade": 4.5,
      "admission_type": "коммерция",
      "needs_dormitory": false,
      "priority_enrollment": "none",
      "preferential_enrollment": "none",
      "enrolled": false,
      "submitted_at": "2025-06-02T10:30:00Z"
    }
  },
  {
    "model": "applicant.applicant",
    "pk": 3,
    "fields": {
      "full_name": "Новиков Максим Михайлович",
      "citizenship": "Россия",
      "nationality": "fdfd",
      "birth_date": "2025-05-30",
      "birth_place": "г. Нижнекамск",
      "address": "fsdf",
      "address_actual": "sdsdfsdfs",
      "passport_division_code": "123123",
      "passport_registration_date": "2025-05-27",
      "certificate_series": "12345678912345",
      "certificate_issued_date": "2025-06-01",
      "graduation_year": 2025,
      "graduation_institution": "Школа №50",
      "passport_series": "9372",
      "passport_number": "376631",
      "passport_issued_by": "УФМС по РТ",
      "passport_issued_date": "2025-05-30",
      "inn": "158476830356",
      "snils": "45345435435",
      "medical_policy": "ОМС",
      "military_id": false,
      "student_phone": "+7-999-805-70-16",
      "student_email": "on3ginnn@gmail.com",
      "mother_name": "Кузнецов Анна Александровна",
      "mother_phone": "+7-919-938-54-44",
      "mother_job": "Школа №5, учитель",
      "mother_passport_series": "1234",
      "mother_passport_number": "123456",
      "mother_passport_issued_by": "sadfdsf",
      "mother_passport_issued_date": "2025-05-28",
      "father_name": "Смирнов Алина Егорович",
      "father_phone": "+7-941-436-35-58",
      "father_job": "Завод, инженер",
      "father_passport_series": "1234",
      "father_passport_number": "123456",
      "father_passport_issued_by": "sdfsdfsd",
      "father_passport_issued_date": "2025-06-05",
      "documents_delivered": true,
      "specialty": "pharmacy_9",
      "grade_russian": 3,
      "grade_biology": 4,
      "grade_chemistry": 5,
      "grade_math": 3,
      "grade_language": 4,
      "grade_physics": 5,
      "average_grade": 4.0,
      "admission_type": "бюджет",
      "needs_dormitory": true,
      "priority_enrollment": "none",
      "preferential_enrollment": "none",
      "enrolled": false,
      "submitted_at": "2025-06-10T18:11:49.954Z"
    }
  }
]